README.md
aamp_app.py
command_invoker.py
command_sequence.py
console_interceptor.py
mongodb_helper.py
recipe_tool.py
util.py
aamp_app/__init__.py
aamp_app/aamp_app.py
aamp_app/command_invoker.py
aamp_app/command_sequence.py
aamp_app/console_interceptor.py
aamp_app/mongodb_helper.py
aamp_app/util.py
aamp_app/commands/__init__.py
aamp_app/commands/command.py
aamp_app/commands/dummy_composite_commands.py
aamp_app/commands/dummy_heater_commands.py
aamp_app/commands/dummy_meter_commands.py
aamp_app/commands/dummy_motor_commands.py
aamp_app/commands/festo_solenoid_valve_commands.py
aamp_app/commands/generic_commands.py
aamp_app/commands/heating_stage_commands.py
aamp_app/commands/keithley_2450_commands.py
aamp_app/commands/kinova_arm_commands.py
aamp_app/commands/linear_stage_150_commands.py
aamp_app/commands/mfc_commands.py
aamp_app/commands/mts50_z8_commands.py
aamp_app/commands/multi_stepper_commands.py
aamp_app/commands/newport_esp301_commands.py
aamp_app/commands/oxygen_sensor_commands.py
aamp_app/commands/psd6_syringe_pump_commands.py
aamp_app/commands/sht85_sensor_commands.py
aamp_app/commands/stellarnet_spectrometer_commands.py
aamp_app/commands/utility_commands.py
aamp_app/commands/ximea_camera_commands.py
aamp_app/devices/__init__.py
aamp_app/devices/device.py
aamp_app/devices/dummy_heater.py
aamp_app/devices/dummy_meter.py
aamp_app/devices/dummy_motor.py
aamp_app/devices/dummy_motor_source.py
aamp_app/devices/festo_solenoid_valve.py
aamp_app/devices/heating_stage.py
aamp_app/devices/keithley_2450.py
aamp_app/devices/kinova_arm.py
aamp_app/devices/linear_stage_150.py
aamp_app/devices/mfc.py
aamp_app/devices/mts50_z8.py
aamp_app/devices/multi_stepper.py
aamp_app/devices/newport_esp301.py
aamp_app/devices/oxygen_sensor.py
aamp_app/devices/psd6_syringe_pump.py
aamp_app/devices/sht85_sensor.py
aamp_app/devices/stellarnet_spectrometer.py
aamp_app/devices/utility_device.py
aamp_app/devices/ximea_camera.py
aamp_app/pages/data.py
aamp_app/pages/database.py
aamp_app.egg-info/PKG-INFO
aamp_app.egg-info/SOURCES.txt
aamp_app.egg-info/dependency_links.txt
aamp_app.egg-info/entry_points.txt
aamp_app.egg-info/requires.txt
aamp_app.egg-info/top_level.txt
aamp_app-0.0.1.30.dist-info/METADATA
aamp_app-0.0.1.30.dist-info/WHEEL
aamp_app-0.0.1.30.dist-info/entry_points.txt
aamp_app-0.0.1.30.dist-info/top_level.txt
aamp_app-0.0.1.30.dist-info/RECORD
