Metadata-Version: 2.1
Name: aamp-app
Version: 0.0.1.30
Summary: AAMP App
Author: Piyush Pahuja
Classifier: Programming Language :: Python :: 3
Classifier: License :: OSI Approved :: MIT License
Classifier: Operating System :: OS Independent
Requires-Python: >=3.10
Requires-Dist: certifi
Requires-Dist: colorama
Requires-Dist: dash
Requires-Dist: dash-ace
Requires-Dist: dash-bootstrap-components
Requires-Dist: dash-table
Requires-Dist: mfc
Requires-Dist: pandas
Requires-Dist: pdoc
Requires-Dist: Pillow
Requires-Dist: pymongo
Requires-Dist: pyserial
Requires-Dist: PyVISA
Requires-Dist: pyyaml
Requires-Dist: questionary
Requires-Dist: scipy
Requires-Dist: slackclient
Requires-Dist: ximea-py
Requires-Dist: pyfirmata
